{
  "description": {
    "name": "Hostel Marilena",
    "description": "Cheap accomodation in Dragolm for anyone. Good connection with city centre via public transport. Cyclicsts, backpackers welcome. Reception is open 24/7.",
    "location": {
      "latitude": 45.9348412,
      "longitude": 24.0123480
    },
    "contacts": {
      "general": {
        "email": "info@marilena.ro",
        "phone": "004013248875",
        "url": "https://geotowns.ro/marilena"
      }
    },
    "address": {
      "line1": "Horse Saddle 34",
      "line2": "",
      "postalCode": "33200",
      "city": "Dragolm",
      "country": "RO"
    },
    "timezone": "Europe/Bucharest",
    "currency": "RON",
    "amenities": [
       "vending machine",
       "laundromat"
    ],
    "images": [
      "building1.jpg",
      "building2.jpg",
      "laundromat.jpg"
    ],
    "roomTypes": {
      "shared-room-4": {
        "name": "Four-bed shared room",
        "description": "All rooms are equipped with safes. Some of them have a window.",
        "totalQuantity": 64,
        "occupancy": {
          "min": 1,
          "max": 1
        },
        "amenities": [
          "safe"
        ],
        "images": [
          "four-bed-room.jpg"
        ],
        "properties": {
          "nonSmoking": "all"
        }
      },
      "shared-room-12": {
        "name": "Twelve-bed shared room",
        "description": "All rooms have windows and are equipped with safes. In each room, there are six bunk beds.",
        "totalQuantity": 48,
        "occupancy": {
          "min": 1,
          "max": 1
        },
        "amenities": [
          "safe"
        ],
        "images": [
          "bunk-beds.jpg",
          "bunk-beds2.jpg"
        ],
        "properties": {
          "nonSmoking": "all"
        }
      }
    },
    "cancellationPolicies": [
      {
        "from": "2018-01-01",
        "to": "2019-12-31",
        "deadline": 14,
        "amount": 50
      }
    ]
  },
  "ratePlans": {
    "shared-room-4-2018": {
      "name": "Four-bed shared room (2018)",
      "description": "Price per person per night for the four bed shared room. Cleaning fee not included.",
      "currency": "RON",
      "price": 40,
      "roomTypeIds": ["shared-room-4"],
      "availableForReservation": {
        "from": "2018-01-01",
        "to": "2018-12-31"
      },
      "availableForTravel": {
        "from": "2018-01-01",
        "to": "2018-12-31"
      }
    },
    "shared-room-12-2018": {
      "name": "Twelve-bed shared room (2018)",
      "description": "Price per person per night for the twelve bed shared room. Cleaning fee not included.",
      "currency": "RON",
      "price": 26,
      "roomTypeIds": ["shared-room-12"],
      "availableForReservation": {
        "from": "2018-01-01",
        "to": "2018-12-31"
      },
      "availableForTravel": {
        "from": "2018-01-01",
        "to": "2018-12-31"
      }
    },
    "shared-room-4-2019": {
      "name": "Four-bed shared room (2019)",
      "description": "Price per person per night for the four bed shared room. Cleaning fee not included.",
      "currency": "RON",
      "price": 42,
      "roomTypeIds": ["shared-room-4"],
      "availableForReservation": {
        "from": "2018-01-01",
        "to": "2019-12-31"
      },
      "availableForTravel": {
        "from": "2019-01-01",
        "to": "2019-12-31"
      }
    },
    "shared-room-12-2019": {
      "name": "Twelve-bed shared room (2019)",
      "description": "Price per person per night for the twelve bed shared room. Cleaning fee not included.",
      "currency": "RON",
      "price": 27,
      "roomTypeIds": ["shared-room-12"],
      "availableForReservation": {
        "from": "2018-01-01",
        "to": "2019-12-31"
      },
      "availableForTravel": {
        "from": "2019-01-01",
        "to": "2019-12-31"
      }
    }
  }
}
